myCodeLibrary/__init__.py
myCodeLibrary-0.1.dist-info/LICENSE.txt
myCodeLibrary-0.1.dist-info/METADATA
myCodeLibrary-0.1.dist-info/WHEEL
myCodeLibrary-0.1.dist-info/top_level.txt
myCodeLibrary-0.1.dist-info/RECORD
