Metadata-Version: 2.1
Name: myCodeLibrary
Version: 0.1
Summary: calculations
Author: Chennakesavulu G
Author-email: chennakesavulu.g@impetus.com
License-File: LICENSE.txt
